README
setup.py
TurboClearsilver.egg-info/PKG-INFO
TurboClearsilver.egg-info/SOURCES.txt
TurboClearsilver.egg-info/entry_points.txt
TurboClearsilver.egg-info/top_level.txt
TurboClearsilver.egg-info/zip-safe
turboclearsilver/__init__.py
turboclearsilver/clearsilver.py
turboclearsilver/cssupport.py
