Metadata-Version: 1.0
Name: TurboClearsilver
Version: 0.2
Summary: Clearsilver plugin for TurboGears and Buffet
Home-page: http://embassy.asylumware.com/projects/turboclearsilver
Author: John Hampton
Author-email: pacopablo@asylumware.com
License: UNKNOWN
Platform: UNKNOWN
Classifier: Development Status :: 3 - Alpha
Classifier: Operating System :: OS Independent
Classifier: Programming Language :: Python
Classifier: License :: OSI Approved :: MIT License
Classifier: Topic :: Software Development :: Libraries :: Python Modules
